SimpliPyTEM/App_functions.py
SimpliPyTEM/MicroVideo_class.py
SimpliPyTEM/Micrograph_class.py
SimpliPyTEM/Motion_correction.py
SimpliPyTEM/PDF_generator.py
SimpliPyTEM/Particle_analysis.py
SimpliPyTEM/Particle_tracking.py
SimpliPyTEM/SimpliPyTEM_GUI.py
SimpliPyTEM/html_writer.py
SimpliPyTEM-1.0.11.dist-info/LICENSE
SimpliPyTEM-1.0.11.dist-info/METADATA
SimpliPyTEM-1.0.11.dist-info/WHEEL
SimpliPyTEM-1.0.11.dist-info/entry_points.txt
SimpliPyTEM-1.0.11.dist-info/top_level.txt
SimpliPyTEM-1.0.11.dist-info/RECORD
