Metadata-Version: 2.1
Name: SimpliPyTEM
Version: 1.0.11
Summary: A python package to simplify the processing and analysis of TEM and in situ TEM images and videos
Home-page: https://github/gabriel-ing/Micrograph-analysis-scripts
Author: Gabriel Ing
Author-email: ucbtgrb@ucl.ac.uk
License: GPL-3.0
Classifier: Development Status :: 4 - Beta
Classifier: Intended Audience :: Science/Research
Classifier: License :: OSI Approved :: BSD License
Classifier: Operating System :: POSIX :: Linux
Classifier: Programming Language :: Python :: 3
Classifier: Topic :: Scientific/Engineering :: Image Processing
License-File: LICENSE
Requires-Dist: numpy
Requires-Dist: ncempy ==1.10.0
Requires-Dist: Pillow ==10.2.0
Requires-Dist: mrcfile ==1.4.3
Requires-Dist: moviepy ==1.0.3
Requires-Dist: airium ==0.2.5
Requires-Dist: matplotlib
Requires-Dist: opencv-python ==4.7.0.72
Requires-Dist: tifffile ==2023.3.21
Requires-Dist: notebook ==7.0.0b2
Requires-Dist: scikit-image ==0.20.0
Requires-Dist: imutils ==0.5.4
Requires-Dist: fpdf2 ==2.7.5
Requires-Dist: PyQt6 ==6.5.0
Requires-Dist: sphinx
Requires-Dist: sphinx-rtd-theme
Requires-Dist: nbsphinx
Requires-Dist: pandas ==1.5.3
Requires-Dist: seaborn ==0.12.2
Requires-Dist: hyperspy ==1.7.5
Requires-Dist: cherrypicker ==0.4.0
Requires-Dist: imagecodecs
